ou_container_builder/__about__.py
ou_container_builder/__init__.py
ou_container_builder/__main__.py
ou_container_builder/settings.py
ou_container_builder/state.py
ou_container_builder/util.py
ou_container_builder/cli/__init__.py
ou_container_builder/cli/base.py
ou_container_builder/cli/build.py
ou_container_builder/cli/clean.py
ou_container_builder/cli/generate.py
ou_container_builder/cli/version.py
ou_container_builder/core/__init__.py
ou_container_builder/core/apt.py
ou_container_builder/core/args.py
ou_container_builder/core/base.py
ou_container_builder/core/content.py
ou_container_builder/core/environment.py
ou_container_builder/core/python.py
ou_container_builder/core/rust.py
ou_container_builder/core/scripts.py
ou_container_builder/core/services.py
ou_container_builder/core/sources.py
ou_container_builder/core/user.py
ou_container_builder/core/webapp.py
ou_container_builder/core/server/__init__.py
ou_container_builder/core/server/startup.py
ou_container_builder/packs/__init__.py
ou_container_builder/packs/ipykernel.py
ou_container_builder/packs/irkernel.py
ou_container_builder/packs/jupyterlab.py
ou_container_builder/packs/notebook.py
ou_container_builder/packs/code_server/__init__.py
ou_container_builder/packs/code_server/vscode.svg
ou_container_builder/packs/xfce4/__init__.py
ou_container_builder/packs/xfce4/desktop.jpg
ou_container_builder/packs/xfce4/xfce4-desktop.xml
ou_container_builder/packs/xfce4/xfwm4.xml
ou_container_builder-3.6.0.dist-info/METADATA
ou_container_builder-3.6.0.dist-info/WHEEL
ou_container_builder-3.6.0.dist-info/entry_points.txt
ou_container_builder-3.6.0.dist-info/RECORD
