Metadata-Version: 2.4
Name: ou-container-builder
Version: 3.6.0
Project-URL: Documentation, https://github.com/unknown/ou-container-builder#readme
Project-URL: Issues, https://github.com/unknown/ou-container-builder/issues
Project-URL: Source, https://github.com/unknown/ou-container-builder
Author-email: Mark Hall <mark.hall@work.room3b.eu>
License-Expression: MIT
Classifier: Development Status :: 4 - Beta
Classifier: Programming Language :: Python
Classifier: Programming Language :: Python :: 3.10
Classifier: Programming Language :: Python :: 3.11
Classifier: Programming Language :: Python :: Implementation :: CPython
Classifier: Programming Language :: Python :: Implementation :: PyPy
Requires-Python: >=3.10
Requires-Dist: jinja2<4,>=3
Requires-Dist: pydantic<3,>=2
Requires-Dist: pyyaml<7,>=6
Requires-Dist: rich<14,>=13
Requires-Dist: typer
